panda3d_render_pass/__init__.py
panda3d_render_pass/renderpass.py
panda3d_render_pass-0.1.1.dist-info/LICENSE
panda3d_render_pass-0.1.1.dist-info/WHEEL
panda3d_render_pass-0.1.1.dist-info/METADATA
panda3d_render_pass-0.1.1.dist-info/RECORD
