Metadata-Version: 2.1
Name: panda3d-render-pass
Version: 0.1.1
Summary: A Panda3D utility to simplify setting up multi-pass rendering systems
Home-page: https://github.com/Kupoman/panda3d-render-pass
License: MIT
Author: Daniel Stokes
Author-email: kupomail@gmail.com
Requires-Python: >=3.7,<4.0
Classifier: Development Status :: 3 - Alpha
Classifier: License :: OSI Approved :: MIT License
Classifier: Programming Language :: Python :: 3
Classifier: Programming Language :: Python :: 3.7
Requires-Dist: panda3d (>=1.10,<2.0)
Project-URL: Documentation, https://github.com/Kupoman/panda3d-render-pass
Project-URL: Repository, https://github.com/Kupoman/panda3d-render-pass
